deephaven_plugin_datetimeinput/__init__.py
deephaven_plugin_datetimeinput/deephaven_plugin_datetimeinput_object.py
deephaven_plugin_datetimeinput/deephaven_plugin_datetimeinput_type.py
deephaven_plugin_datetimeinput/js_plugin.py
deephaven_plugin_datetimeinput/register.py
deephaven_plugin_datetimeinput/_js/package.json
deephaven_plugin_datetimeinput/_js/dist/index.js
deephaven_plugin_datetimeinput-0.2.0.dist-info/LICENSE
deephaven_plugin_datetimeinput-0.2.0.dist-info/METADATA
deephaven_plugin_datetimeinput-0.2.0.dist-info/WHEEL
deephaven_plugin_datetimeinput-0.2.0.dist-info/entry_points.txt
deephaven_plugin_datetimeinput-0.2.0.dist-info/top_level.txt
deephaven_plugin_datetimeinput-0.2.0.dist-info/RECORD
